LICENSE
MANIFEST.in
README.md
setup.cfg
setup.py
brisktyper/__init__.py
brisktyper/__main__.py
brisktyper/ani.py
brisktyper/blast.py
brisktyper/mlst.py
brisktyper/print_final_results.py
brisktyper.egg-info/PKG-INFO
brisktyper.egg-info/SOURCES.txt
brisktyper.egg-info/dependency_links.txt
brisktyper.egg-info/entry_points.txt
brisktyper.egg-info/not-zip-safe
brisktyper.egg-info/requires.txt
brisktyper.egg-info/top_level.txt
brisktyper/seq_ani_db/__init__.py
brisktyper/seq_ani_db/cytotoxicity/__init__.py
brisktyper/seq_ani_db/cytotoxicity/cytotoxicity.tsv
brisktyper/seq_ani_db/geneflow/__init__.py
brisktyper/seq_ani_db/geneflow/geneflow.tsv
brisktyper/seq_ani_db/species/__init__.py
brisktyper/seq_ani_db/species/species.tsv
brisktyper/seq_ani_db/subspecies/__init__.py
brisktyper/seq_ani_db/subspecies/subspecies.tsv
brisktyper/seq_ani_db/typestrains/__init__.py
brisktyper/seq_ani_db/typestrains/typestrains.tsv
brisktyper/seq_bt_db/__init__.py
brisktyper/seq_bt_db/brisktyper_bt_sequences.faa
brisktyper/seq_bt_db/btyper3_bt_sequences.faa
brisktyper/seq_mlst_db/__init__.py
brisktyper/seq_mlst_db/pubmlst.xml
brisktyper/seq_panC_db/__init__.py
brisktyper/seq_panC_db/panC.fna
brisktyper/seq_virulence_db/__init__.py
brisktyper/seq_virulence_db/brisktyper_virulence_sequences.faa
brisktyper/seq_virulence_db/brisktyper_virulence_sequences.ffn
brisktyper/seq_virulence_db/btyper3_virulence_sequences.faa
brisktyper/seq_virulence_db/btyper3_virulence_sequences.ffn